imfp/__init__.py
imfp/admin.py
imfp/data.py
imfp/utils.py
imfp-1.3.0.dist-info/licenses/LICENSE
imfp-1.3.0.dist-info/METADATA
imfp-1.3.0.dist-info/WHEEL
imfp-1.3.0.dist-info/top_level.txt
imfp-1.3.0.dist-info/RECORD
