Metadata-Version: 2.4
Name: imfp
Version: 1.3.0
Summary: Python package for downloading economic data from the International Monetary Fund JSON RESTful API endpoint.
Author-email: "Christopher C. Smith" <christopher.smith@promptlytechnologies.com>
License:                                  Apache License
Project-URL: homepage, https://promptlytechnologies.com/imfp
Project-URL: repository, https://github.com/Promptly-Technologies-LLC/imfp
Keywords: economics,finance,IMF,API
Classifier: Intended Audience :: Financial and Insurance Industry
Classifier: Programming Language :: Python :: 3
Classifier: License :: OSI Approved :: MIT License
Classifier: Operating System :: OS Independent
Requires-Python: >=3.10
License-File: LICENSE
Requires-Dist: pandas==2.2.3
Requires-Dist: requests==2.32.4
Requires-Dist: type-enforced>=1.10.1
Dynamic: license-file
